easyeasyplot/__init__.py
easyeasyplot/command.py
easyeasyplot/plot.py
easyeasyplot-0.1.0.dist-info/LICENSE
easyeasyplot-0.1.0.dist-info/WHEEL
easyeasyplot-0.1.0.dist-info/METADATA
easyeasyplot-0.1.0.dist-info/RECORD
