Metadata-Version: 2.1
Name: easyeasyplot
Version: 0.1.0
Summary: 
License: MIT
Author: acse-dx121
Author-email: dx121@ic.ac.uk
Requires-Python: >=3.8,<4.0
Classifier: License :: OSI Approved :: MIT License
Classifier: Programming Language :: Python :: 3
Classifier: Programming Language :: Python :: 3.8
Classifier: Programming Language :: Python :: 3.9
Classifier: Programming Language :: Python :: 3.10
Requires-Dist: matplotlib (>=3.6.0,<4.0.0)
Requires-Dist: numpy (>=1.23.3,<2.0.0)
